{
    "checksum": "c7da7f5f4b59eee2d8c6fa812b3efb6ec9a6e91d73a2857ad1ed86eb69c7783e",
    "file": "watch",
    "mime": {
        "encoding": "us-ascii",
        "type": "text/plain"
    },
    "number_of_duplicates": 1,
    "package": "surf-display",
    "path": "surf-display/0.0.5-2/debian/watch",
    "pkg_infos": {
        "area": "main",
        "copyright": true,
        "ctags_count": 0,
        "license": "/copyright/license/surf-display/0.0.5-2/",
        "metric": {
            "size": 140
        },
        "pts_link": "https://tracker.debian.org/pkg/surf-display",
        "sloc": [
            [
                "sh",
                226
            ],
            [
                "makefile",
                42
            ]
        ],
        "suites": [
            "bookworm",
            "bullseye",
            "buster",
            "sid"
        ],
        "vcs_browser": "https://salsa.debian.org/debian-edu-pkg-team/surf-display",
        "vcs_type": "git"
    },
    "raw_url": "/data/main/s/surf-display/0.0.5-2/debian/watch",
    "stat": {
        "perms": "rw-r--r--",
        "size": 113,
        "symlink_dest": null,
        "type": "-"
    },
    "text_file": true,
    "type": "file",
    "version": "0.0.5-2"
}