{
    "checksum": "0f357fa82b380e98b647591231aca899c31bb37b6da75f1d4bcc02b5de63f6d9",
    "file": "cosint.m",
    "mime": {
        "encoding": "us-ascii",
        "type": "text/plain"
    },
    "number_of_duplicates": 4,
    "package": "octave-specfun",
    "path": "octave-specfun/1.1.0-7/inst/cosint.m",
    "pkg_infos": {
        "area": "main",
        "copyright": true,
        "ctags_count": 0,
        "license": "/copyright/license/octave-specfun/1.1.0-7/",
        "metric": {
            "size": 236
        },
        "pts_link": "https://tracker.debian.org/pkg/octave-specfun",
        "sloc": [
            [
                "objc",
                459
            ],
            [
                "cpp",
                275
            ],
            [
                "makefile",
                11
            ]
        ],
        "suites": [
            "bookworm",
            "bullseye",
            "sid"
        ],
        "vcs_browser": "https://salsa.debian.org/pkg-octave-team/octave-specfun",
        "vcs_type": "git"
    },
    "raw_url": "/data/main/o/octave-specfun/1.1.0-7/inst/cosint.m",
    "stat": {
        "perms": "rw-r--r--",
        "size": 1171,
        "symlink_dest": null,
        "type": "-"
    },
    "text_file": true,
    "type": "file",
    "version": "1.1.0-7"
}