{
    "checksum": "c40b986562c8ee7f37a77126f0895f0e8d29e0ecea13c8110392e3bb22431433",
    "file": "module_list.html",
    "mime": {
        "encoding": "us-ascii",
        "type": "text/html"
    },
    "number_of_duplicates": 8,
    "package": "refpolicy",
    "path": "refpolicy/2:2.20210203-7/doc/templates/module_list.html",
    "pkg_infos": {
        "area": "main",
        "copyright": true,
        "ctags_count": 0,
        "license": "/copyright/license/refpolicy/2:2.20210203-7/",
        "metric": {
            "size": 16044
        },
        "pts_link": "https://tracker.debian.org/pkg/refpolicy",
        "sloc": [
            [
                "python",
                2171
            ],
            [
                "makefile",
                626
            ],
            [
                "sh",
                174
            ],
            [
                "sed",
                21
            ],
            [
                "xml",
                13
            ],
            [
                "awk",
                7
            ]
        ],
        "suites": [
            "bookworm",
            "bullseye",
            "sid"
        ],
        "vcs_browser": "https://salsa.debian.org/selinux-team/refpolicy",
        "vcs_type": "git"
    },
    "raw_url": "/data/main/r/refpolicy/2%3A2.20210203-7/doc/templates/module_list.html",
    "stat": {
        "perms": "rw-r--r--",
        "size": 492,
        "symlink_dest": null,
        "type": "-"
    },
    "text_file": true,
    "type": "file",
    "version": "2:2.20210203-7"
}