{
    "checksum": "7450b1c702d8b2cb7fa91513ef5a35a1933723d482acc9b79aba161dc25eac9e",
    "file": "packaging-recommendations.mdwn",
    "mime": {
        "encoding": "us-ascii",
        "type": "text/plain"
    },
    "number_of_duplicates": 1,
    "package": "git-stuff",
    "path": "git-stuff/11-1/docs/packaging-recommendations.mdwn",
    "pkg_infos": {
        "area": "main",
        "copyright": true,
        "ctags_count": 0,
        "license": "/copyright/license/git-stuff/11-1/",
        "metric": {
            "size": 468
        },
        "pts_link": "https://tracker.debian.org/pkg/git-stuff",
        "sloc": [
            [
                "sh",
                1072
            ],
            [
                "perl",
                152
            ],
            [
                "makefile",
                128
            ]
        ],
        "suites": [
            "wheezy"
        ]
    },
    "raw_url": "/data/main/g/git-stuff/11-1/docs/packaging-recommendations.mdwn",
    "stat": {
        "perms": "rw-r--r--",
        "size": 6532,
        "symlink_dest": null,
        "type": "-"
    },
    "text_file": true,
    "type": "file",
    "version": "11-1"
}