{
    "checksum": "50447921577762e1bff24326aeaed3d9b3d7e03fe5f7c85a1108ba1a5add4019",
    "file": "day_archive.htm",
    "mime": {
        "encoding": "us-ascii",
        "type": "text/html"
    },
    "number_of_duplicates": 1,
    "package": "nanoblogger",
    "path": "nanoblogger/3.4.2-3/default/templates/day_archive.htm",
    "pkg_infos": {
        "area": "main",
        "copyright": true,
        "ctags_count": 188,
        "license": "/copyright/license/nanoblogger/3.4.2-3/",
        "metric": {
            "size": 704
        },
        "pts_link": "https://tracker.debian.org/pkg/nanoblogger",
        "sloc": [
            [
                "sh",
                3598
            ],
            [
                "makefile",
                2
            ]
        ],
        "suites": [
            "buster",
            "jessie",
            "jessie-kfreebsd",
            "squeeze",
            "stretch",
            "wheezy"
        ]
    },
    "raw_url": "/data/main/n/nanoblogger/3.4.2-3/default/templates/day_archive.htm",
    "stat": {
        "perms": "rw-r--r--",
        "size": 1738,
        "symlink_dest": null,
        "type": "-"
    },
    "text_file": true,
    "type": "file",
    "version": "3.4.2-3"
}