{
    "content": [
        {
            "hidden": false,
            "name": "README.Debian",
            "stat": {
                "perms": "rw-r--r--",
                "size": 205,
                "symlink_dest": null,
                "type": "-"
            },
            "type": "file"
        },
        {
            "hidden": false,
            "name": "changelog",
            "stat": {
                "perms": "rw-r--r--",
                "size": 3913,
                "symlink_dest": null,
                "type": "-"
            },
            "type": "file"
        },
        {
            "hidden": false,
            "name": "compat",
            "stat": {
                "perms": "rw-r--r--",
                "size": 2,
                "symlink_dest": null,
                "type": "-"
            },
            "type": "file"
        },
        {
            "hidden": false,
            "name": "control",
            "stat": {
                "perms": "rw-r--r--",
                "size": 522,
                "symlink_dest": null,
                "type": "-"
            },
            "type": "file"
        },
        {
            "hidden": false,
            "name": "copyright",
            "stat": {
                "perms": "rw-r--r--",
                "size": 1085,
                "symlink_dest": null,
                "type": "-"
            },
            "type": "file"
        },
        {
            "hidden": false,
            "name": "dirs",
            "stat": {
                "perms": "rw-r--r--",
                "size": 93,
                "symlink_dest": null,
                "type": "-"
            },
            "type": "file"
        },
        {
            "hidden": false,
            "name": "docs",
            "stat": {
                "perms": "rw-r--r--",
                "size": 20,
                "symlink_dest": null,
                "type": "-"
            },
            "type": "file"
        },
        {
            "hidden": false,
            "name": "examples",
            "stat": {
                "perms": "rw-r--r--",
                "size": 62,
                "symlink_dest": null,
                "type": "-"
            },
            "type": "file"
        },
        {
            "hidden": false,
            "name": "gpsim-led.lintian",
            "stat": {
                "perms": "rw-r--r--",
                "size": 66,
                "symlink_dest": null,
                "type": "-"
            },
            "type": "file"
        },
        {
            "hidden": false,
            "name": "rules",
            "stat": {
                "perms": "rwxr-xr-x",
                "size": 2270,
                "symlink_dest": null,
                "type": "-"
            },
            "type": "file"
        }
    ],
    "directory": "debian",
    "package": "gpsim-led",
    "path": "gpsim-led/0.22.0~rc3-2/debian",
    "pkg_infos": {
        "area": "main",
        "copyright": true,
        "ctags_count": 126,
        "license": "/copyright/license/gpsim-led/0.22.0%7Erc3-2/",
        "metric": {
            "size": 1576
        },
        "pts_link": "https://tracker.debian.org/pkg/gpsim-led",
        "sloc": [
            [
                "sh",
                10827
            ],
            [
                "cpp",
                591
            ],
            [
                "makefile",
                67
            ],
            [
                "asm",
                36
            ]
        ],
        "suites": [
            "etch",
            "etch-m68k",
            "lenny"
        ]
    },
    "type": "directory",
    "version": "0.22.0~rc3-2"
}