{
    "content": [
        {
            "hidden": false,
            "name": "napiprojektdownloadengine.cpp",
            "stat": {
                "perms": "rw-r--r--",
                "size": 7949,
                "symlink_dest": null,
                "type": "-"
            },
            "type": "file"
        },
        {
            "hidden": false,
            "name": "napiprojektdownloadengine.h",
            "stat": {
                "perms": "rw-r--r--",
                "size": 1968,
                "symlink_dest": null,
                "type": "-"
            },
            "type": "file"
        },
        {
            "hidden": false,
            "name": "napisy24downloadengine.cpp",
            "stat": {
                "perms": "rw-r--r--",
                "size": 11419,
                "symlink_dest": null,
                "type": "-"
            },
            "type": "file"
        },
        {
            "hidden": false,
            "name": "napisy24downloadengine.h",
            "stat": {
                "perms": "rw-r--r--",
                "size": 1858,
                "symlink_dest": null,
                "type": "-"
            },
            "type": "file"
        },
        {
            "hidden": false,
            "name": "opensubtitlesdownloadengine.cpp",
            "stat": {
                "perms": "rw-r--r--",
                "size": 7858,
                "symlink_dest": null,
                "type": "-"
            },
            "type": "file"
        },
        {
            "hidden": false,
            "name": "opensubtitlesdownloadengine.h",
            "stat": {
                "perms": "rw-r--r--",
                "size": 2018,
                "symlink_dest": null,
                "type": "-"
            },
            "type": "file"
        },
        {
            "hidden": false,
            "name": "subtitledownloadengine.cpp",
            "stat": {
                "perms": "rw-r--r--",
                "size": 2029,
                "symlink_dest": null,
                "type": "-"
            },
            "type": "file"
        },
        {
            "hidden": false,
            "name": "subtitledownloadengine.h",
            "stat": {
                "perms": "rw-r--r--",
                "size": 1886,
                "symlink_dest": null,
                "type": "-"
            },
            "type": "file"
        },
        {
            "hidden": false,
            "name": "subtitledownloadenginemetadata.h",
            "stat": {
                "perms": "rw-r--r--",
                "size": 1543,
                "symlink_dest": null,
                "type": "-"
            },
            "type": "file"
        },
        {
            "hidden": false,
            "name": "subtitledownloadenginesregistry.cpp",
            "stat": {
                "perms": "rw-r--r--",
                "size": 4938,
                "symlink_dest": null,
                "type": "-"
            },
            "type": "file"
        },
        {
            "hidden": false,
            "name": "subtitledownloadenginesregistry.h",
            "stat": {
                "perms": "rw-r--r--",
                "size": 2042,
                "symlink_dest": null,
                "type": "-"
            },
            "type": "file"
        }
    ],
    "directory": "engines",
    "package": "qnapi",
    "path": "qnapi/0.2.3-2/libqnapi/src/engines",
    "pkg_infos": {
        "area": "main",
        "copyright": true,
        "ctags_count": 0,
        "license": "/copyright/license/qnapi/0.2.3-2/",
        "metric": {
            "size": 3328
        },
        "pts_link": "https://tracker.debian.org/pkg/qnapi",
        "sloc": [
            [
                "cpp",
                8634
            ],
            [
                "sh",
                49
            ],
            [
                "makefile",
                10
            ]
        ],
        "suites": [
            "bullseye",
            "sid"
        ]
    },
    "type": "directory",
    "version": "0.2.3-2"
}