{
    "content": [
        {
            "hidden": false,
            "name": "Makefile.am",
            "stat": {
                "perms": "rw-r--r--",
                "size": 907,
                "symlink_dest": null,
                "type": "-"
            },
            "type": "file"
        },
        {
            "hidden": false,
            "name": "Makefile.in",
            "stat": {
                "perms": "rw-r--r--",
                "size": 25188,
                "symlink_dest": null,
                "type": "-"
            },
            "type": "file"
        },
        {
            "hidden": false,
            "name": "ddc_async.c",
            "stat": {
                "perms": "rwxr-xr-x",
                "size": 2101,
                "symlink_dest": null,
                "type": "-"
            },
            "type": "file"
        },
        {
            "hidden": false,
            "name": "ddc_async.h",
            "stat": {
                "perms": "rwxr-xr-x",
                "size": 610,
                "symlink_dest": null,
                "type": "-"
            },
            "type": "file"
        },
        {
            "hidden": false,
            "name": "ddc_display_lock.c",
            "stat": {
                "perms": "rw-r--r--",
                "size": 8488,
                "symlink_dest": null,
                "type": "-"
            },
            "type": "file"
        },
        {
            "hidden": false,
            "name": "ddc_display_lock.h",
            "stat": {
                "perms": "rw-r--r--",
                "size": 853,
                "symlink_dest": null,
                "type": "-"
            },
            "type": "file"
        },
        {
            "hidden": false,
            "name": "ddc_displays.c",
            "stat": {
                "perms": "rw-r--r--",
                "size": 36630,
                "symlink_dest": null,
                "type": "-"
            },
            "type": "file"
        },
        {
            "hidden": false,
            "name": "ddc_displays.h",
            "stat": {
                "perms": "rw-r--r--",
                "size": 1608,
                "symlink_dest": null,
                "type": "-"
            },
            "type": "file"
        },
        {
            "hidden": false,
            "name": "ddc_dumpload.c",
            "stat": {
                "perms": "rwxr-xr-x",
                "size": 28626,
                "symlink_dest": null,
                "type": "-"
            },
            "type": "file"
        },
        {
            "hidden": false,
            "name": "ddc_dumpload.h",
            "stat": {
                "perms": "rwxr-xr-x",
                "size": 2209,
                "symlink_dest": null,
                "type": "-"
            },
            "type": "file"
        },
        {
            "hidden": false,
            "name": "ddc_multi_part_io.c",
            "stat": {
                "perms": "rw-r--r--",
                "size": 14638,
                "symlink_dest": null,
                "type": "-"
            },
            "type": "file"
        },
        {
            "hidden": false,
            "name": "ddc_multi_part_io.h",
            "stat": {
                "perms": "rw-r--r--",
                "size": 974,
                "symlink_dest": null,
                "type": "-"
            },
            "type": "file"
        },
        {
            "hidden": false,
            "name": "ddc_output.c",
            "stat": {
                "perms": "rw-r--r--",
                "size": 32382,
                "symlink_dest": null,
                "type": "-"
            },
            "type": "file"
        },
        {
            "hidden": false,
            "name": "ddc_output.h",
            "stat": {
                "perms": "rw-r--r--",
                "size": 2018,
                "symlink_dest": null,
                "type": "-"
            },
            "type": "file"
        },
        {
            "hidden": false,
            "name": "ddc_packet_io.c",
            "stat": {
                "perms": "rw-r--r--",
                "size": 33566,
                "symlink_dest": null,
                "type": "-"
            },
            "type": "file"
        },
        {
            "hidden": false,
            "name": "ddc_packet_io.h",
            "stat": {
                "perms": "rw-r--r--",
                "size": 1619,
                "symlink_dest": null,
                "type": "-"
            },
            "type": "file"
        },
        {
            "hidden": false,
            "name": "ddc_read_capabilities.c",
            "stat": {
                "perms": "rw-r--r--",
                "size": 5079,
                "symlink_dest": null,
                "type": "-"
            },
            "type": "file"
        },
        {
            "hidden": false,
            "name": "ddc_read_capabilities.h",
            "stat": {
                "perms": "rwxr-xr-x",
                "size": 520,
                "symlink_dest": null,
                "type": "-"
            },
            "type": "file"
        },
        {
            "hidden": false,
            "name": "ddc_services.c",
            "stat": {
                "perms": "rw-r--r--",
                "size": 4136,
                "symlink_dest": null,
                "type": "-"
            },
            "type": "file"
        },
        {
            "hidden": false,
            "name": "ddc_services.h",
            "stat": {
                "perms": "rw-r--r--",
                "size": 511,
                "symlink_dest": null,
                "type": "-"
            },
            "type": "file"
        },
        {
            "hidden": false,
            "name": "ddc_strategy.c",
            "stat": {
                "perms": "rw-r--r--",
                "size": 989,
                "symlink_dest": null,
                "type": "-"
            },
            "type": "file"
        },
        {
            "hidden": false,
            "name": "ddc_strategy.h",
            "stat": {
                "perms": "rw-r--r--",
                "size": 769,
                "symlink_dest": null,
                "type": "-"
            },
            "type": "file"
        },
        {
            "hidden": false,
            "name": "ddc_try_stats.c",
            "stat": {
                "perms": "rw-r--r--",
                "size": 15674,
                "symlink_dest": null,
                "type": "-"
            },
            "type": "file"
        },
        {
            "hidden": false,
            "name": "ddc_try_stats.h",
            "stat": {
                "perms": "rw-r--r--",
                "size": 926,
                "symlink_dest": null,
                "type": "-"
            },
            "type": "file"
        },
        {
            "hidden": false,
            "name": "ddc_vcp.c",
            "stat": {
                "perms": "rw-r--r--",
                "size": 26620,
                "symlink_dest": null,
                "type": "-"
            },
            "type": "file"
        },
        {
            "hidden": false,
            "name": "ddc_vcp.h",
            "stat": {
                "perms": "rwxr-xr-x",
                "size": 1554,
                "symlink_dest": null,
                "type": "-"
            },
            "type": "file"
        },
        {
            "hidden": false,
            "name": "ddc_vcp_version.c",
            "stat": {
                "perms": "rwxr-xr-x",
                "size": 5633,
                "symlink_dest": null,
                "type": "-"
            },
            "type": "file"
        },
        {
            "hidden": false,
            "name": "ddc_vcp_version.h",
            "stat": {
                "perms": "rwxr-xr-x",
                "size": 646,
                "symlink_dest": null,
                "type": "-"
            },
            "type": "file"
        },
        {
            "hidden": false,
            "name": "ddc_watch_displays.c",
            "stat": {
                "perms": "rw-r--r--",
                "size": 15018,
                "symlink_dest": null,
                "type": "-"
            },
            "type": "file"
        },
        {
            "hidden": false,
            "name": "ddc_watch_displays.h",
            "stat": {
                "perms": "rw-r--r--",
                "size": 1349,
                "symlink_dest": null,
                "type": "-"
            },
            "type": "file"
        },
        {
            "hidden": false,
            "name": "new",
            "stat": {
                "perms": "rwxr-xr-x",
                "size": 40,
                "symlink_dest": null,
                "type": "d"
            },
            "type": "directory"
        },
        {
            "hidden": false,
            "name": "old",
            "stat": {
                "perms": "rwxr-xr-x",
                "size": 53,
                "symlink_dest": null,
                "type": "d"
            },
            "type": "directory"
        }
    ],
    "directory": "ddc",
    "package": "ddcutil",
    "path": "ddcutil/0.9.9-2/src/ddc",
    "pkg_infos": {
        "area": "main",
        "copyright": true,
        "ctags_count": 0,
        "license": "/copyright/license/ddcutil/0.9.9-2/",
        "metric": {
            "size": 6708
        },
        "pts_link": "https://tracker.debian.org/pkg/ddcutil",
        "sloc": [
            [
                "ansic",
                50073
            ],
            [
                "sh",
                4540
            ],
            [
                "makefile",
                1060
            ],
            [
                "python",
                24
            ]
        ],
        "suites": [
            "bullseye"
        ]
    },
    "type": "directory",
    "version": "0.9.9-2"
}