{
    "checksum": "acc37f87c33f98dbe424e750341df53d5a88412c440f671ed66f9b5cdb08bbab",
    "file": "ViewAdapter.java",
    "mime": {
        "encoding": "us-ascii",
        "type": "text/x-java"
    },
    "number_of_duplicates": 2,
    "package": "jajuk",
    "path": "jajuk/1:1.10.9+dfsg2-4/src/main/java/org/jajuk/ui/views/ViewAdapter.java",
    "pkg_infos": {
        "area": "main",
        "copyright": true,
        "ctags_count": 0,
        "license": "/copyright/license/jajuk/1:1.10.9+dfsg2-4/",
        "metric": {
            "size": 10240
        },
        "pts_link": "https://tracker.debian.org/pkg/jajuk",
        "sloc": [
            [
                "java",
                68193
            ],
            [
                "xml",
                996
            ],
            [
                "sh",
                78
            ],
            [
                "makefile",
                15
            ]
        ],
        "suites": [
            "sid"
        ],
        "vcs_browser": "https://anonscm.debian.org/cgit/pkg-java/jajuk.git",
        "vcs_type": "git"
    },
    "raw_url": "/data/main/j/jajuk/1%3A1.10.9%2Bdfsg2-4/src/main/java/org/jajuk/ui/views/ViewAdapter.java",
    "stat": {
        "perms": "rw-r--r--",
        "size": 6652,
        "symlink_dest": null,
        "type": "-"
    },
    "text_file": true,
    "type": "file",
    "version": "1:1.10.9+dfsg2-4"
}