{
    "checksum": "0587ffa9630dc966e4f297f2cbb98a3818748557e6a57062dc6c10803626e5dd",
    "file": "utils.py",
    "mime": {
        "encoding": "us-ascii",
        "type": "text/x-python"
    },
    "number_of_duplicates": 1,
    "package": "gnat-gps",
    "path": "gnat-gps/19.2-3/.pc/python_2_to_3.diff/share/support/core/gps_utils/internal/utils.py",
    "pkg_infos": {
        "area": "main",
        "copyright": true,
        "ctags_count": 0,
        "license": "/copyright/license/gnat-gps/19.2-3/",
        "metric": {
            "size": 45236
        },
        "pts_link": "https://tracker.debian.org/pkg/gnat-gps",
        "sloc": [
            [
                "ada",
                366795
            ],
            [
                "python",
                32902
            ],
            [
                "xml",
                9699
            ],
            [
                "makefile",
                1025
            ],
            [
                "ansic",
                917
            ],
            [
                "sh",
                320
            ],
            [
                "java",
                17
            ]
        ],
        "suites": [
            "sid"
        ],
        "vcs_browser": "https://salsa.debian.org/debian/gnat-gps",
        "vcs_type": "git"
    },
    "raw_url": "/data/main/g/gnat-gps/19.2-3/.pc/python_2_to_3.diff/share/support/core/gps_utils/internal/utils.py",
    "stat": {
        "perms": "rw-r--r--",
        "size": 32285,
        "symlink_dest": null,
        "type": "-"
    },
    "text_file": true,
    "type": "file",
    "version": "19.2-3"
}