{
    "checksum": "8cf8e17b5ed371bb5f1ccc1ed1ede5765a38926cfaf9cb745ba4abf6f931d51a",
    "file": "D11StateBlock.cpp",
    "mime": {
        "encoding": "us-ascii",
        "type": "text/x-c"
    },
    "number_of_duplicates": 2,
    "package": "mumble",
    "path": "mumble/1.3.4-1/overlay/D11StateBlock.cpp",
    "pkg_infos": {
        "area": "main",
        "copyright": true,
        "ctags_count": 0,
        "license": "/copyright/license/mumble/1.3.4-1/",
        "metric": {
            "size": 43580
        },
        "pts_link": "https://tracker.debian.org/pkg/mumble",
        "sloc": [
            [
                "ansic",
                150503
            ],
            [
                "cpp",
                71684
            ],
            [
                "xml",
                14417
            ],
            [
                "python",
                2207
            ],
            [
                "perl",
                1225
            ],
            [
                "sh",
                1064
            ],
            [
                "makefile",
                685
            ],
            [
                "asm",
                360
            ],
            [
                "php",
                344
            ],
            [
                "cs",
                55
            ],
            [
                "objc",
                42
            ],
            [
                "ruby",
                37
            ]
        ],
        "suites": [
            "bookworm",
            "sid"
        ],
        "vcs_browser": "https://salsa.debian.org/pkg-voip-team/mumble",
        "vcs_type": "git"
    },
    "raw_url": "/data/main/m/mumble/1.3.4-1/overlay/D11StateBlock.cpp",
    "stat": {
        "perms": "rw-r--r--",
        "size": 5067,
        "symlink_dest": null,
        "type": "-"
    },
    "text_file": true,
    "type": "file",
    "version": "1.3.4-1"
}