{
    "content": [
        {
            "hidden": false,
            "name": "Compiler",
            "stat": {
                "perms": "rwxr-xr-x",
                "size": 4096,
                "symlink_dest": null,
                "type": "d"
            },
            "type": "directory"
        },
        {
            "hidden": false,
            "name": "Interpreter",
            "stat": {
                "perms": "rwxr-xr-x",
                "size": 4096,
                "symlink_dest": null,
                "type": "d"
            },
            "type": "directory"
        },
        {
            "hidden": false,
            "name": "MakeSelfRunner",
            "stat": {
                "perms": "rwxr-xr-x",
                "size": 95,
                "symlink_dest": null,
                "type": "d"
            },
            "type": "directory"
        },
        {
            "hidden": false,
            "name": "custom_alloc.c",
            "stat": {
                "perms": "rw-r--r--",
                "size": 1951,
                "symlink_dest": null,
                "type": "-"
            },
            "type": "file"
        },
        {
            "hidden": false,
            "name": "dialogUtils.c",
            "stat": {
                "perms": "rw-r--r--",
                "size": 6364,
                "symlink_dest": null,
                "type": "-"
            },
            "type": "file"
        },
        {
            "hidden": false,
            "name": "dialogUtils.h",
            "stat": {
                "perms": "rw-r--r--",
                "size": 1000,
                "symlink_dest": null,
                "type": "-"
            },
            "type": "file"
        },
        {
            "hidden": false,
            "name": "dialogutils.r",
            "stat": {
                "perms": "rw-r--r--",
                "size": 332,
                "symlink_dest": null,
                "type": "-"
            },
            "type": "file"
        },
        {
            "hidden": false,
            "name": "makeSelfRunner.c",
            "stat": {
                "perms": "rw-r--r--",
                "size": 6833,
                "symlink_dest": null,
                "type": "-"
            },
            "type": "file"
        },
        {
            "hidden": false,
            "name": "makeSelfRunner.h",
            "stat": {
                "perms": "rw-r--r--",
                "size": 370,
                "symlink_dest": null,
                "type": "-"
            },
            "type": "file"
        },
        {
            "hidden": false,
            "name": "makeSelfRunnerMain.c",
            "stat": {
                "perms": "rw-r--r--",
                "size": 1237,
                "symlink_dest": null,
                "type": "-"
            },
            "type": "file"
        },
        {
            "hidden": false,
            "name": "mindyIcons.r",
            "stat": {
                "perms": "rw-r--r--",
                "size": 34773,
                "symlink_dest": null,
                "type": "-"
            },
            "type": "file"
        },
        {
            "hidden": false,
            "name": "pool_alloc.plugin.c",
            "stat": {
                "perms": "rw-r--r--",
                "size": 4456,
                "symlink_dest": null,
                "type": "-"
            },
            "type": "file"
        },
        {
            "hidden": false,
            "name": "pool_alloc_dropin.c",
            "stat": {
                "perms": "rwxr-xr-x",
                "size": 1508,
                "symlink_dest": null,
                "type": "-"
            },
            "type": "file"
        },
        {
            "hidden": false,
            "name": "selfRunner.rsrc",
            "stat": {
                "perms": "rw-r--r--",
                "size": 3266,
                "symlink_dest": null,
                "type": "-"
            },
            "type": "file"
        },
        {
            "hidden": false,
            "name": "selfRunnerTest.c",
            "stat": {
                "perms": "rw-r--r--",
                "size": 1257,
                "symlink_dest": null,
                "type": "-"
            },
            "type": "file"
        }
    ],
    "directory": "MacSource",
    "package": "gwydion-dylan",
    "path": "gwydion-dylan/2.3.8pre1-1/mindy/Macintosh/MacSource",
    "pkg_infos": {
        "area": "main",
        "copyright": true,
        "ctags_count": 11695,
        "license": "/copyright/license/gwydion-dylan/2.3.8pre1-1/",
        "metric": {
            "size": 20700
        },
        "pts_link": "https://tracker.debian.org/pkg/gwydion-dylan",
        "sloc": [
            [
                "ansic",
                75723
            ],
            [
                "lisp",
                2992
            ],
            [
                "sh",
                2194
            ],
            [
                "cpp",
                2022
            ],
            [
                "perl",
                1729
            ],
            [
                "yacc",
                1281
            ],
            [
                "makefile",
                856
            ],
            [
                "asm",
                412
            ],
            [
                "lex",
                296
            ]
        ],
        "suites": [
            "woody"
        ]
    },
    "type": "directory",
    "version": "2.3.8pre1-1"
}