{
    "content": [
        {
            "hidden": false,
            "name": "BreakpointHandle.cs",
            "stat": {
                "perms": "rw-r--r--",
                "size": 3398,
                "symlink_dest": null,
                "type": "-"
            },
            "type": "file"
        },
        {
            "hidden": false,
            "name": "BreakpointManager.cs",
            "stat": {
                "perms": "rw-r--r--",
                "size": 7618,
                "symlink_dest": null,
                "type": "-"
            },
            "type": "file"
        },
        {
            "hidden": false,
            "name": "DebuggerServant.cs",
            "stat": {
                "perms": "rw-r--r--",
                "size": 8414,
                "symlink_dest": null,
                "type": "-"
            },
            "type": "file"
        },
        {
            "hidden": false,
            "name": "EventQueue.cs",
            "stat": {
                "perms": "rw-r--r--",
                "size": 4405,
                "symlink_dest": null,
                "type": "-"
            },
            "type": "file"
        },
        {
            "hidden": false,
            "name": "Inferior.cs",
            "stat": {
                "perms": "rw-r--r--",
                "size": 47769,
                "symlink_dest": null,
                "type": "-"
            },
            "type": "file"
        },
        {
            "hidden": false,
            "name": "Makefile.am",
            "stat": {
                "perms": "rw-r--r--",
                "size": 59,
                "symlink_dest": null,
                "type": "-"
            },
            "type": "file"
        },
        {
            "hidden": false,
            "name": "Makefile.in",
            "stat": {
                "perms": "rw-r--r--",
                "size": 15691,
                "symlink_dest": null,
                "type": "-"
            },
            "type": "file"
        },
        {
            "hidden": false,
            "name": "ProcessServant.cs",
            "stat": {
                "perms": "rw-r--r--",
                "size": 26194,
                "symlink_dest": null,
                "type": "-"
            },
            "type": "file"
        },
        {
            "hidden": false,
            "name": "ProcessStart.cs",
            "stat": {
                "perms": "rw-r--r--",
                "size": 7788,
                "symlink_dest": null,
                "type": "-"
            },
            "type": "file"
        },
        {
            "hidden": false,
            "name": "SingleSteppingEngine.cs",
            "stat": {
                "perms": "rw-r--r--",
                "size": 147795,
                "symlink_dest": null,
                "type": "-"
            },
            "type": "file"
        },
        {
            "hidden": false,
            "name": "SymbolTableManager.cs",
            "stat": {
                "perms": "rw-r--r--",
                "size": 2569,
                "symlink_dest": null,
                "type": "-"
            },
            "type": "file"
        },
        {
            "hidden": false,
            "name": "TargetAccess.cs",
            "stat": {
                "perms": "rw-r--r--",
                "size": 323,
                "symlink_dest": null,
                "type": "-"
            },
            "type": "file"
        },
        {
            "hidden": false,
            "name": "TargetMemoryAccess.cs",
            "stat": {
                "perms": "rw-r--r--",
                "size": 1569,
                "symlink_dest": null,
                "type": "-"
            },
            "type": "file"
        },
        {
            "hidden": false,
            "name": "TargetReader.cs",
            "stat": {
                "perms": "rw-r--r--",
                "size": 4296,
                "symlink_dest": null,
                "type": "-"
            },
            "type": "file"
        },
        {
            "hidden": false,
            "name": "ThreadDB.cs",
            "stat": {
                "perms": "rw-r--r--",
                "size": 4738,
                "symlink_dest": null,
                "type": "-"
            },
            "type": "file"
        },
        {
            "hidden": false,
            "name": "ThreadManager.cs",
            "stat": {
                "perms": "rw-r--r--",
                "size": 20560,
                "symlink_dest": null,
                "type": "-"
            },
            "type": "file"
        },
        {
            "hidden": false,
            "name": "ThreadServant.cs",
            "stat": {
                "perms": "rw-r--r--",
                "size": 8140,
                "symlink_dest": null,
                "type": "-"
            },
            "type": "file"
        },
        {
            "hidden": false,
            "name": "arch",
            "stat": {
                "perms": "rwxr-xr-x",
                "size": 4096,
                "symlink_dest": null,
                "type": "d"
            },
            "type": "directory"
        },
        {
            "hidden": false,
            "name": "mono",
            "stat": {
                "perms": "rwxr-xr-x",
                "size": 4096,
                "symlink_dest": null,
                "type": "d"
            },
            "type": "directory"
        },
        {
            "hidden": false,
            "name": "os",
            "stat": {
                "perms": "rwxr-xr-x",
                "size": 4096,
                "symlink_dest": null,
                "type": "d"
            },
            "type": "directory"
        },
        {
            "hidden": false,
            "name": "server",
            "stat": {
                "perms": "rwxr-xr-x",
                "size": 4096,
                "symlink_dest": null,
                "type": "d"
            },
            "type": "directory"
        }
    ],
    "directory": "backend",
    "package": "mono-debugger",
    "path": "mono-debugger/2.6.3-2.2/backend",
    "pkg_infos": {
        "area": "main",
        "copyright": true,
        "ctags_count": 25095,
        "license": "/copyright/license/mono-debugger/2.6.3-2.2/",
        "metric": {
            "size": 10256
        },
        "pts_link": "https://tracker.debian.org/pkg/mono-debugger",
        "sloc": [
            [
                "ansic",
                100569
            ],
            [
                "cs",
                56054
            ],
            [
                "sh",
                10298
            ],
            [
                "makefile",
                533
            ]
        ],
        "suites": [
            "squeeze"
        ],
        "vcs_browser": "http://svn.debian.org/wsvn/pkg-mono/mono-debugger/trunk/",
        "vcs_type": "svn"
    },
    "type": "directory",
    "version": "2.6.3-2.2"
}