{
    "checksum": "2626000e5243f3a2296da4278f7347ce6f575cf6175cc9c986085e6591aab8a6",
    "file": ".travis.yml",
    "mime": {
        "encoding": "us-ascii",
        "type": "text/plain"
    },
    "number_of_duplicates": 45,
    "package": "easygen",
    "path": "easygen/4.1.0-1/.travis.yml",
    "pkg_infos": {
        "area": "main",
        "copyright": true,
        "ctags_count": 0,
        "license": "/copyright/license/easygen/4.1.0-1/",
        "metric": {
            "size": 672
        },
        "pts_link": "https://tracker.debian.org/pkg/easygen",
        "sloc": [
            [
                "makefile",
                18
            ],
            [
                "sh",
                14
            ]
        ],
        "suites": [
            "bookworm",
            "bullseye",
            "sid"
        ],
        "vcs_browser": "https://salsa.debian.org/go-team/packages/easygen",
        "vcs_type": "git"
    },
    "raw_url": "/data/main/e/easygen/4.1.0-1/.travis.yml",
    "stat": {
        "perms": "rw-r--r--",
        "size": 13,
        "symlink_dest": null,
        "type": "-"
    },
    "text_file": true,
    "type": "file",
    "version": "4.1.0-1"
}