{
    "content": [
        {
            "hidden": false,
            "name": "changelog",
            "stat": {
                "perms": "rw-r--r--",
                "size": 3176,
                "symlink_dest": null,
                "type": "-"
            },
            "type": "file"
        },
        {
            "hidden": false,
            "name": "control",
            "stat": {
                "perms": "rw-r--r--",
                "size": 1134,
                "symlink_dest": null,
                "type": "-"
            },
            "type": "file"
        },
        {
            "hidden": false,
            "name": "copyright",
            "stat": {
                "perms": "rw-r--r--",
                "size": 2098,
                "symlink_dest": null,
                "type": "-"
            },
            "type": "file"
        },
        {
            "hidden": false,
            "name": "docs",
            "stat": {
                "perms": "rw-r--r--",
                "size": 10,
                "symlink_dest": null,
                "type": "-"
            },
            "type": "file"
        },
        {
            "hidden": false,
            "name": "gbp.conf",
            "stat": {
                "perms": "rw-r--r--",
                "size": 95,
                "symlink_dest": null,
                "type": "-"
            },
            "type": "file"
        },
        {
            "hidden": false,
            "name": "nodejs",
            "stat": {
                "perms": "rwxr-xr-x",
                "size": 26,
                "symlink_dest": null,
                "type": "d"
            },
            "type": "directory"
        },
        {
            "hidden": false,
            "name": "patches",
            "stat": {
                "perms": "rwxr-xr-x",
                "size": 59,
                "symlink_dest": null,
                "type": "d"
            },
            "type": "directory"
        },
        {
            "hidden": false,
            "name": "rules",
            "stat": {
                "perms": "rwxr-xr-x",
                "size": 94,
                "symlink_dest": null,
                "type": "-"
            },
            "type": "file"
        },
        {
            "hidden": false,
            "name": "salsa-ci.yml",
            "stat": {
                "perms": "rw-r--r--",
                "size": 170,
                "symlink_dest": null,
                "type": "-"
            },
            "type": "file"
        },
        {
            "hidden": false,
            "name": "source",
            "stat": {
                "perms": "rwxr-xr-x",
                "size": 27,
                "symlink_dest": null,
                "type": "d"
            },
            "type": "directory"
        },
        {
            "hidden": false,
            "name": "upstream",
            "stat": {
                "perms": "rwxr-xr-x",
                "size": 29,
                "symlink_dest": null,
                "type": "d"
            },
            "type": "directory"
        },
        {
            "hidden": false,
            "name": "watch",
            "stat": {
                "perms": "rw-r--r--",
                "size": 318,
                "symlink_dest": null,
                "type": "-"
            },
            "type": "file"
        }
    ],
    "directory": "debian",
    "package": "node-regenerator-transform",
    "path": "node-regenerator-transform/0.14.5-4/debian",
    "pkg_infos": {
        "area": "main",
        "copyright": true,
        "ctags_count": 0,
        "license": "/copyright/license/node-regenerator-transform/0.14.5-4/",
        "metric": {
            "size": 252
        },
        "pts_link": "https://tracker.debian.org/pkg/node-regenerator-transform",
        "sloc": [
            [
                "javascript",
                2689
            ],
            [
                "makefile",
                2
            ]
        ],
        "suites": [
            "bookworm",
            "bullseye",
            "sid"
        ],
        "vcs_browser": "https://salsa.debian.org/js-team/node-regenerator-transform",
        "vcs_type": "git"
    },
    "type": "directory",
    "version": "0.14.5-4"
}