{
    "content": [
        {
            "hidden": false,
            "name": "Makefile",
            "stat": {
                "perms": "rw-r--r--",
                "size": 463,
                "symlink_dest": null,
                "type": "-"
            },
            "type": "file"
        },
        {
            "hidden": false,
            "name": "p1.m",
            "stat": {
                "perms": "rw-r--r--",
                "size": 423,
                "symlink_dest": null,
                "type": "-"
            },
            "type": "file"
        },
        {
            "hidden": false,
            "name": "p11.m",
            "stat": {
                "perms": "rw-r--r--",
                "size": 682,
                "symlink_dest": null,
                "type": "-"
            },
            "type": "file"
        },
        {
            "hidden": false,
            "name": "p12.m",
            "stat": {
                "perms": "rw-r--r--",
                "size": 238,
                "symlink_dest": null,
                "type": "-"
            },
            "type": "file"
        },
        {
            "hidden": false,
            "name": "p13.m",
            "stat": {
                "perms": "rw-r--r--",
                "size": 175,
                "symlink_dest": null,
                "type": "-"
            },
            "type": "file"
        },
        {
            "hidden": false,
            "name": "p14.m",
            "stat": {
                "perms": "rw-r--r--",
                "size": 627,
                "symlink_dest": null,
                "type": "-"
            },
            "type": "file"
        },
        {
            "hidden": false,
            "name": "p19.m",
            "stat": {
                "perms": "rw-r--r--",
                "size": 1285,
                "symlink_dest": null,
                "type": "-"
            },
            "type": "file"
        },
        {
            "hidden": false,
            "name": "p2.m",
            "stat": {
                "perms": "rw-r--r--",
                "size": 239,
                "symlink_dest": null,
                "type": "-"
            },
            "type": "file"
        },
        {
            "hidden": false,
            "name": "p20.m",
            "stat": {
                "perms": "rw-r--r--",
                "size": 276,
                "symlink_dest": null,
                "type": "-"
            },
            "type": "file"
        },
        {
            "hidden": false,
            "name": "p3.m",
            "stat": {
                "perms": "rw-r--r--",
                "size": 533,
                "symlink_dest": null,
                "type": "-"
            },
            "type": "file"
        },
        {
            "hidden": false,
            "name": "p4.m",
            "stat": {
                "perms": "rw-r--r--",
                "size": 113,
                "symlink_dest": null,
                "type": "-"
            },
            "type": "file"
        },
        {
            "hidden": false,
            "name": "p5.m",
            "stat": {
                "perms": "rw-r--r--",
                "size": 144,
                "symlink_dest": null,
                "type": "-"
            },
            "type": "file"
        },
        {
            "hidden": false,
            "name": "p6.m",
            "stat": {
                "perms": "rw-r--r--",
                "size": 96,
                "symlink_dest": null,
                "type": "-"
            },
            "type": "file"
        },
        {
            "hidden": false,
            "name": "p7.m",
            "stat": {
                "perms": "rw-r--r--",
                "size": 257,
                "symlink_dest": null,
                "type": "-"
            },
            "type": "file"
        },
        {
            "hidden": false,
            "name": "p8.m",
            "stat": {
                "perms": "rw-r--r--",
                "size": 118,
                "symlink_dest": null,
                "type": "-"
            },
            "type": "file"
        },
        {
            "hidden": false,
            "name": "p9.m",
            "stat": {
                "perms": "rw-r--r--",
                "size": 257,
                "symlink_dest": null,
                "type": "-"
            },
            "type": "file"
        },
        {
            "hidden": false,
            "name": "plcdemos.h",
            "stat": {
                "perms": "rw-r--r--",
                "size": 1126,
                "symlink_dest": null,
                "type": "-"
            },
            "type": "file"
        },
        {
            "hidden": false,
            "name": "plplot_octave_demo.m",
            "stat": {
                "perms": "rw-r--r--",
                "size": 853,
                "symlink_dest": null,
                "type": "-"
            },
            "type": "file"
        },
        {
            "hidden": false,
            "name": "x01c.c",
            "stat": {
                "perms": "rw-r--r--",
                "size": 7124,
                "symlink_dest": null,
                "type": "-"
            },
            "type": "file"
        },
        {
            "hidden": false,
            "name": "x01c.m",
            "stat": {
                "perms": "rw-r--r--",
                "size": 4501,
                "symlink_dest": null,
                "type": "-"
            },
            "type": "file"
        },
        {
            "hidden": false,
            "name": "x02c.c",
            "stat": {
                "perms": "rw-r--r--",
                "size": 1927,
                "symlink_dest": null,
                "type": "-"
            },
            "type": "file"
        },
        {
            "hidden": false,
            "name": "x02c.m",
            "stat": {
                "perms": "rw-r--r--",
                "size": 710,
                "symlink_dest": null,
                "type": "-"
            },
            "type": "file"
        },
        {
            "hidden": false,
            "name": "x03c.c",
            "stat": {
                "perms": "rw-r--r--",
                "size": 2549,
                "symlink_dest": null,
                "type": "-"
            },
            "type": "file"
        },
        {
            "hidden": false,
            "name": "x03c.m",
            "stat": {
                "perms": "rw-r--r--",
                "size": 1396,
                "symlink_dest": null,
                "type": "-"
            },
            "type": "file"
        },
        {
            "hidden": false,
            "name": "x04c.c",
            "stat": {
                "perms": "rw-r--r--",
                "size": 3223,
                "symlink_dest": null,
                "type": "-"
            },
            "type": "file"
        },
        {
            "hidden": false,
            "name": "x04c.m",
            "stat": {
                "perms": "rw-r--r--",
                "size": 1592,
                "symlink_dest": null,
                "type": "-"
            },
            "type": "file"
        },
        {
            "hidden": false,
            "name": "x05c.c",
            "stat": {
                "perms": "rw-r--r--",
                "size": 1724,
                "symlink_dest": null,
                "type": "-"
            },
            "type": "file"
        },
        {
            "hidden": false,
            "name": "x05c.m",
            "stat": {
                "perms": "rw-r--r--",
                "size": 551,
                "symlink_dest": null,
                "type": "-"
            },
            "type": "file"
        },
        {
            "hidden": false,
            "name": "x06c.c",
            "stat": {
                "perms": "rw-r--r--",
                "size": 2283,
                "symlink_dest": null,
                "type": "-"
            },
            "type": "file"
        },
        {
            "hidden": false,
            "name": "x06c.m",
            "stat": {
                "perms": "rw-r--r--",
                "size": 1100,
                "symlink_dest": null,
                "type": "-"
            },
            "type": "file"
        },
        {
            "hidden": false,
            "name": "x07c.c",
            "stat": {
                "perms": "rw-r--r--",
                "size": 2424,
                "symlink_dest": null,
                "type": "-"
            },
            "type": "file"
        },
        {
            "hidden": false,
            "name": "x07c.m",
            "stat": {
                "perms": "rw-r--r--",
                "size": 1160,
                "symlink_dest": null,
                "type": "-"
            },
            "type": "file"
        },
        {
            "hidden": false,
            "name": "x08c.c",
            "stat": {
                "perms": "rw-r--r--",
                "size": 2906,
                "symlink_dest": null,
                "type": "-"
            },
            "type": "file"
        },
        {
            "hidden": false,
            "name": "x08c.m",
            "stat": {
                "perms": "rw-r--r--",
                "size": 1453,
                "symlink_dest": null,
                "type": "-"
            },
            "type": "file"
        },
        {
            "hidden": false,
            "name": "x09c.c",
            "stat": {
                "perms": "rw-r--r--",
                "size": 4323,
                "symlink_dest": null,
                "type": "-"
            },
            "type": "file"
        },
        {
            "hidden": false,
            "name": "x09c.m",
            "stat": {
                "perms": "rw-r--r--",
                "size": 2361,
                "symlink_dest": null,
                "type": "-"
            },
            "type": "file"
        },
        {
            "hidden": false,
            "name": "x10c.c",
            "stat": {
                "perms": "rw-r--r--",
                "size": 1677,
                "symlink_dest": null,
                "type": "-"
            },
            "type": "file"
        },
        {
            "hidden": false,
            "name": "x10c.m",
            "stat": {
                "perms": "rw-r--r--",
                "size": 599,
                "symlink_dest": null,
                "type": "-"
            },
            "type": "file"
        },
        {
            "hidden": false,
            "name": "x11c.c",
            "stat": {
                "perms": "rw-r--r--",
                "size": 3202,
                "symlink_dest": null,
                "type": "-"
            },
            "type": "file"
        },
        {
            "hidden": false,
            "name": "x11c.m",
            "stat": {
                "perms": "rw-r--r--",
                "size": 1415,
                "symlink_dest": null,
                "type": "-"
            },
            "type": "file"
        },
        {
            "hidden": false,
            "name": "x12c.c",
            "stat": {
                "perms": "rw-r--r--",
                "size": 2842,
                "symlink_dest": null,
                "type": "-"
            },
            "type": "file"
        },
        {
            "hidden": false,
            "name": "x12c.m",
            "stat": {
                "perms": "rw-r--r--",
                "size": 1133,
                "symlink_dest": null,
                "type": "-"
            },
            "type": "file"
        },
        {
            "hidden": false,
            "name": "x13c.c",
            "stat": {
                "perms": "rw-r--r--",
                "size": 2498,
                "symlink_dest": null,
                "type": "-"
            },
            "type": "file"
        },
        {
            "hidden": false,
            "name": "x13c.m",
            "stat": {
                "perms": "rw-r--r--",
                "size": 1284,
                "symlink_dest": null,
                "type": "-"
            },
            "type": "file"
        },
        {
            "hidden": false,
            "name": "x14c.c",
            "stat": {
                "perms": "rw-r--r--",
                "size": 9491,
                "symlink_dest": null,
                "type": "-"
            },
            "type": "file"
        },
        {
            "hidden": false,
            "name": "x14c.m",
            "stat": {
                "perms": "rw-r--r--",
                "size": 6747,
                "symlink_dest": null,
                "type": "-"
            },
            "type": "file"
        },
        {
            "hidden": false,
            "name": "x15c.c",
            "stat": {
                "perms": "rw-r--r--",
                "size": 7380,
                "symlink_dest": null,
                "type": "-"
            },
            "type": "file"
        },
        {
            "hidden": false,
            "name": "x15c.m",
            "stat": {
                "perms": "rw-r--r--",
                "size": 4293,
                "symlink_dest": null,
                "type": "-"
            },
            "type": "file"
        },
        {
            "hidden": false,
            "name": "x16c.c",
            "stat": {
                "perms": "rw-r--r--",
                "size": 8513,
                "symlink_dest": null,
                "type": "-"
            },
            "type": "file"
        },
        {
            "hidden": false,
            "name": "x16c.m",
            "stat": {
                "perms": "rw-r--r--",
                "size": 3925,
                "symlink_dest": null,
                "type": "-"
            },
            "type": "file"
        },
        {
            "hidden": false,
            "name": "x17c.c",
            "stat": {
                "perms": "rw-r--r--",
                "size": 4223,
                "symlink_dest": null,
                "type": "-"
            },
            "type": "file"
        },
        {
            "hidden": false,
            "name": "x17c.m",
            "stat": {
                "perms": "rw-r--r--",
                "size": 2064,
                "symlink_dest": null,
                "type": "-"
            },
            "type": "file"
        },
        {
            "hidden": false,
            "name": "x18c.c",
            "stat": {
                "perms": "rw-r--r--",
                "size": 4840,
                "symlink_dest": null,
                "type": "-"
            },
            "type": "file"
        },
        {
            "hidden": false,
            "name": "x18c.m",
            "stat": {
                "perms": "rw-r--r--",
                "size": 2778,
                "symlink_dest": null,
                "type": "-"
            },
            "type": "file"
        },
        {
            "hidden": false,
            "name": "x19c.c",
            "stat": {
                "perms": "rw-r--r--",
                "size": 2409,
                "symlink_dest": null,
                "type": "-"
            },
            "type": "file"
        },
        {
            "hidden": false,
            "name": "x19c.m",
            "stat": {
                "perms": "rw-r--r--",
                "size": 201,
                "symlink_dest": null,
                "type": "-"
            },
            "type": "file"
        }
    ],
    "directory": "demos",
    "package": "octave-plplot",
    "path": "octave-plplot/0.3-9/demos",
    "pkg_infos": {
        "area": "main",
        "copyright": true,
        "ctags_count": 1312,
        "license": "/copyright/license/octave-plplot/0.3-9/",
        "metric": {
            "size": 2252
        },
        "pts_link": "https://tracker.debian.org/pkg/octave-plplot",
        "sloc": [
            [
                "cpp",
                3833
            ],
            [
                "ansic",
                2278
            ],
            [
                "perl",
                670
            ],
            [
                "makefile",
                105
            ],
            [
                "sh",
                16
            ]
        ],
        "suites": [
            "potato"
        ]
    },
    "type": "directory",
    "version": "0.3-9"
}