{
    "content": [
        {
            "hidden": false,
            "name": "Makefile.in",
            "percent_encoded_name": "Makefile.in",
            "stat": {
                "perms": "rw-r--r--",
                "size": 41545,
                "symlink_dest": null,
                "type": "-"
            },
            "type": "file"
        },
        {
            "hidden": false,
            "name": "README",
            "percent_encoded_name": "README",
            "stat": {
                "perms": "rw-r--r--",
                "size": 6896,
                "symlink_dest": null,
                "type": "-"
            },
            "type": "file"
        },
        {
            "hidden": false,
            "name": "aclocal.m4",
            "percent_encoded_name": "aclocal.m4",
            "stat": {
                "perms": "rw-r--r--",
                "size": 24,
                "symlink_dest": null,
                "type": "-"
            },
            "type": "file"
        },
        {
            "hidden": false,
            "name": "configure",
            "percent_encoded_name": "configure",
            "stat": {
                "perms": "rwxr-xr-x",
                "size": 149543,
                "symlink_dest": null,
                "type": "-"
            },
            "type": "file"
        },
        {
            "hidden": false,
            "name": "configure.in",
            "percent_encoded_name": "configure.in",
            "stat": {
                "perms": "rwxr-xr-x",
                "size": 16353,
                "symlink_dest": null,
                "type": "-"
            },
            "type": "file"
        },
        {
            "hidden": false,
            "name": "install-sh",
            "percent_encoded_name": "install-sh",
            "stat": {
                "perms": "rwxr-xr-x",
                "size": 2255,
                "symlink_dest": null,
                "type": "-"
            },
            "type": "file"
        },
        {
            "hidden": false,
            "name": "license.terms",
            "percent_encoded_name": "license.terms",
            "stat": {
                "perms": "rw-r--r--",
                "size": 2209,
                "symlink_dest": null,
                "type": "-"
            },
            "type": "file"
        },
        {
            "hidden": false,
            "name": "mkLinks",
            "percent_encoded_name": "mkLinks",
            "stat": {
                "perms": "rwxr-xr-x",
                "size": 21045,
                "symlink_dest": null,
                "type": "-"
            },
            "type": "file"
        },
        {
            "hidden": false,
            "name": "tcl.m4",
            "percent_encoded_name": "tcl.m4",
            "stat": {
                "perms": "rw-r--r--",
                "size": 59154,
                "symlink_dest": null,
                "type": "-"
            },
            "type": "file"
        },
        {
            "hidden": false,
            "name": "tk.spec",
            "percent_encoded_name": "tk.spec",
            "stat": {
                "perms": "rw-r--r--",
                "size": 1763,
                "symlink_dest": null,
                "type": "-"
            },
            "type": "file"
        },
        {
            "hidden": false,
            "name": "tkAppInit.c",
            "percent_encoded_name": "tkAppInit.c",
            "stat": {
                "perms": "rw-r--r--",
                "size": 4046,
                "symlink_dest": null,
                "type": "-"
            },
            "type": "file"
        },
        {
            "hidden": false,
            "name": "tkConfig.sh.in",
            "percent_encoded_name": "tkConfig.sh.in",
            "stat": {
                "perms": "rw-r--r--",
                "size": 3186,
                "symlink_dest": null,
                "type": "-"
            },
            "type": "file"
        },
        {
            "hidden": false,
            "name": "tkUnix.c",
            "percent_encoded_name": "tkUnix.c",
            "stat": {
                "perms": "rw-r--r--",
                "size": 2764,
                "symlink_dest": null,
                "type": "-"
            },
            "type": "file"
        },
        {
            "hidden": false,
            "name": "tkUnix3d.c",
            "percent_encoded_name": "tkUnix3d.c",
            "stat": {
                "perms": "rw-r--r--",
                "size": 14310,
                "symlink_dest": null,
                "type": "-"
            },
            "type": "file"
        },
        {
            "hidden": false,
            "name": "tkUnixButton.c",
            "percent_encoded_name": "tkUnixButton.c",
            "stat": {
                "perms": "rw-r--r--",
                "size": 14317,
                "symlink_dest": null,
                "type": "-"
            },
            "type": "file"
        },
        {
            "hidden": false,
            "name": "tkUnixColor.c",
            "percent_encoded_name": "tkUnixColor.c",
            "stat": {
                "perms": "rw-r--r--",
                "size": 13085,
                "symlink_dest": null,
                "type": "-"
            },
            "type": "file"
        },
        {
            "hidden": false,
            "name": "tkUnixConfig.c",
            "percent_encoded_name": "tkUnixConfig.c",
            "stat": {
                "perms": "rw-r--r--",
                "size": 1177,
                "symlink_dest": null,
                "type": "-"
            },
            "type": "file"
        },
        {
            "hidden": false,
            "name": "tkUnixCursor.c",
            "percent_encoded_name": "tkUnixCursor.c",
            "stat": {
                "perms": "rw-r--r--",
                "size": 11931,
                "symlink_dest": null,
                "type": "-"
            },
            "type": "file"
        },
        {
            "hidden": false,
            "name": "tkUnixDefault.h",
            "percent_encoded_name": "tkUnixDefault.h",
            "stat": {
                "perms": "rw-r--r--",
                "size": 14772,
                "symlink_dest": null,
                "type": "-"
            },
            "type": "file"
        },
        {
            "hidden": false,
            "name": "tkUnixDialog.c",
            "percent_encoded_name": "tkUnixDialog.c",
            "stat": {
                "perms": "rw-r--r--",
                "size": 5719,
                "symlink_dest": null,
                "type": "-"
            },
            "type": "file"
        },
        {
            "hidden": false,
            "name": "tkUnixDraw.c",
            "percent_encoded_name": "tkUnixDraw.c",
            "stat": {
                "perms": "rw-r--r--",
                "size": 5968,
                "symlink_dest": null,
                "type": "-"
            },
            "type": "file"
        },
        {
            "hidden": false,
            "name": "tkUnixEmbed.c",
            "percent_encoded_name": "tkUnixEmbed.c",
            "stat": {
                "perms": "rw-r--r--",
                "size": 31733,
                "symlink_dest": null,
                "type": "-"
            },
            "type": "file"
        },
        {
            "hidden": false,
            "name": "tkUnixEvent.c",
            "percent_encoded_name": "tkUnixEvent.c",
            "stat": {
                "perms": "rw-r--r--",
                "size": 12771,
                "symlink_dest": null,
                "type": "-"
            },
            "type": "file"
        },
        {
            "hidden": false,
            "name": "tkUnixFocus.c",
            "percent_encoded_name": "tkUnixFocus.c",
            "stat": {
                "perms": "rw-r--r--",
                "size": 4635,
                "symlink_dest": null,
                "type": "-"
            },
            "type": "file"
        },
        {
            "hidden": false,
            "name": "tkUnixFont.c",
            "percent_encoded_name": "tkUnixFont.c",
            "stat": {
                "perms": "rw-r--r--",
                "size": 82302,
                "symlink_dest": null,
                "type": "-"
            },
            "type": "file"
        },
        {
            "hidden": false,
            "name": "tkUnixInit.c",
            "percent_encoded_name": "tkUnixInit.c",
            "stat": {
                "perms": "rw-r--r--",
                "size": 2716,
                "symlink_dest": null,
                "type": "-"
            },
            "type": "file"
        },
        {
            "hidden": false,
            "name": "tkUnixInt.h",
            "percent_encoded_name": "tkUnixInt.h",
            "stat": {
                "perms": "rw-r--r--",
                "size": 661,
                "symlink_dest": null,
                "type": "-"
            },
            "type": "file"
        },
        {
            "hidden": false,
            "name": "tkUnixKey.c",
            "percent_encoded_name": "tkUnixKey.c",
            "stat": {
                "perms": "rw-r--r--",
                "size": 9448,
                "symlink_dest": null,
                "type": "-"
            },
            "type": "file"
        },
        {
            "hidden": false,
            "name": "tkUnixMenu.c",
            "percent_encoded_name": "tkUnixMenu.c",
            "stat": {
                "perms": "rw-r--r--",
                "size": 47463,
                "symlink_dest": null,
                "type": "-"
            },
            "type": "file"
        },
        {
            "hidden": false,
            "name": "tkUnixMenubu.c",
            "percent_encoded_name": "tkUnixMenubu.c",
            "stat": {
                "perms": "rw-r--r--",
                "size": 8597,
                "symlink_dest": null,
                "type": "-"
            },
            "type": "file"
        },
        {
            "hidden": false,
            "name": "tkUnixPort.h",
            "percent_encoded_name": "tkUnixPort.h",
            "stat": {
                "perms": "rw-r--r--",
                "size": 5081,
                "symlink_dest": null,
                "type": "-"
            },
            "type": "file"
        },
        {
            "hidden": false,
            "name": "tkUnixScale.c",
            "percent_encoded_name": "tkUnixScale.c",
            "stat": {
                "perms": "rw-r--r--",
                "size": 20846,
                "symlink_dest": null,
                "type": "-"
            },
            "type": "file"
        },
        {
            "hidden": false,
            "name": "tkUnixScrlbr.c",
            "percent_encoded_name": "tkUnixScrlbr.c",
            "stat": {
                "perms": "rw-r--r--",
                "size": 13846,
                "symlink_dest": null,
                "type": "-"
            },
            "type": "file"
        },
        {
            "hidden": false,
            "name": "tkUnixSelect.c",
            "percent_encoded_name": "tkUnixSelect.c",
            "stat": {
                "perms": "rw-r--r--",
                "size": 43357,
                "symlink_dest": null,
                "type": "-"
            },
            "type": "file"
        },
        {
            "hidden": false,
            "name": "tkUnixSend.c",
            "percent_encoded_name": "tkUnixSend.c",
            "stat": {
                "perms": "rw-r--r--",
                "size": 54327,
                "symlink_dest": null,
                "type": "-"
            },
            "type": "file"
        },
        {
            "hidden": false,
            "name": "tkUnixWm.c",
            "percent_encoded_name": "tkUnixWm.c",
            "stat": {
                "perms": "rw-r--r--",
                "size": 151070,
                "symlink_dest": null,
                "type": "-"
            },
            "type": "file"
        },
        {
            "hidden": false,
            "name": "tkUnixXId.c",
            "percent_encoded_name": "tkUnixXId.c",
            "stat": {
                "perms": "rw-r--r--",
                "size": 15911,
                "symlink_dest": null,
                "type": "-"
            },
            "type": "file"
        }
    ],
    "directory": "unix",
    "package": "tk8.3",
    "path": "tk8.3/8.3.5-14/unix",
    "pkg_infos": {
        "area": "main",
        "copyright": true,
        "ctags_count": 12454,
        "license": "/copyright/license/tk8.3/8.3.5-14/",
        "metric": {
            "size": 12500
        },
        "pts_link": "https://tracker.debian.org/pkg/tk8.3",
        "sloc": [
            [
                "ansic",
                120814
            ],
            [
                "tcl",
                13236
            ],
            [
                "makefile",
                1335
            ],
            [
                "sh",
                1196
            ]
        ],
        "suites": [
            "lenny"
        ]
    },
    "type": "directory",
    "version": "8.3.5-14"
}