{
    "content": [
        {
            "hidden": false,
            "name": ".quilt_patches",
            "stat": {
                "perms": "rw-r--r--",
                "size": 15,
                "symlink_dest": null,
                "type": "-"
            },
            "type": "file"
        },
        {
            "hidden": false,
            "name": ".quilt_series",
            "stat": {
                "perms": "rw-r--r--",
                "size": 7,
                "symlink_dest": null,
                "type": "-"
            },
            "type": "file"
        },
        {
            "hidden": false,
            "name": ".version",
            "stat": {
                "perms": "rw-r--r--",
                "size": 2,
                "symlink_dest": null,
                "type": "-"
            },
            "type": "file"
        },
        {
            "hidden": false,
            "name": "Fix-AttributeError-ByteBuffer-object-has-no-attribut.patch",
            "stat": {
                "perms": "rwxr-xr-x",
                "size": 27,
                "symlink_dest": null,
                "type": "d"
            },
            "type": "directory"
        },
        {
            "hidden": false,
            "name": "Fix-SyntaxWarning-is-with-a-literal.-Did-you-mean.patch",
            "stat": {
                "perms": "rwxr-xr-x",
                "size": 27,
                "symlink_dest": null,
                "type": "d"
            },
            "type": "directory"
        },
        {
            "hidden": false,
            "name": "Skip-FRU-test-cases-if-FRU-test-file-is-missing.patch",
            "stat": {
                "perms": "rwxr-xr-x",
                "size": 26,
                "symlink_dest": null,
                "type": "d"
            },
            "type": "directory"
        },
        {
            "hidden": false,
            "name": "Update-to-Python-3.9.patch",
            "stat": {
                "perms": "rwxr-xr-x",
                "size": 43,
                "symlink_dest": null,
                "type": "d"
            },
            "type": "directory"
        },
        {
            "hidden": false,
            "name": "applied-patches",
            "stat": {
                "perms": "rw-r--r--",
                "size": 196,
                "symlink_dest": null,
                "type": "-"
            },
            "type": "file"
        }
    ],
    "directory": ".pc",
    "package": "python-ipmi",
    "path": "python-ipmi/0.4.2-2/.pc",
    "pkg_infos": {
        "area": "main",
        "copyright": true,
        "ctags_count": 0,
        "license": "/copyright/license/python-ipmi/0.4.2-2/",
        "metric": {
            "size": 884
        },
        "pts_link": "https://tracker.debian.org/pkg/python-ipmi",
        "sloc": [
            [
                "python",
                9547
            ],
            [
                "makefile",
                2
            ]
        ],
        "suites": [
            "bookworm",
            "bullseye",
            "sid"
        ],
        "vcs_browser": "https://salsa.debian.org/python-team/packages/python-ipmi",
        "vcs_type": "git"
    },
    "type": "directory",
    "version": "0.4.2-2"
}