{
    "checksum": "686c43a3ecbaa731542a34489c6612a3da9f61e3cc4812e3f092fb5fac5d0f6b",
    "file": "README.md",
    "mime": {
        "encoding": "us-ascii",
        "type": "text/plain"
    },
    "number_of_duplicates": 1,
    "package": "authheaders",
    "path": "authheaders/0.13.0-1/README.md",
    "pkg_infos": {
        "area": "main",
        "copyright": true,
        "ctags_count": 0,
        "license": "/copyright/license/authheaders/0.13.0-1/",
        "metric": {
            "size": 444
        },
        "pts_link": "https://tracker.debian.org/pkg/authheaders",
        "sloc": [
            [
                "python",
                625
            ],
            [
                "makefile",
                14
            ],
            [
                "sh",
                5
            ]
        ],
        "suites": [
            "bookworm",
            "bullseye",
            "sid"
        ],
        "vcs_browser": "https://salsa.debian.org/python-team/modules/authheaders",
        "vcs_type": "git"
    },
    "raw_url": "/data/main/a/authheaders/0.13.0-1/README.md",
    "stat": {
        "perms": "rw-r--r--",
        "size": 3746,
        "symlink_dest": null,
        "type": "-"
    },
    "text_file": true,
    "type": "file",
    "version": "0.13.0-1"
}