{
    "checksum": "67df37d28a46f7902ad081325f4b2471f13c69eb8922639adadcfd66b38e895f",
    "file": "rawstudio.png",
    "mime": {
        "encoding": "binary",
        "type": "image/png"
    },
    "number_of_duplicates": 7,
    "package": "rawstudio",
    "path": "rawstudio/2.0-1.1/pixmaps/rawstudio.png",
    "pkg_infos": {
        "area": "main",
        "copyright": true,
        "ctags_count": 0,
        "license": "/copyright/license/rawstudio/2.0-1.1/",
        "metric": {
            "size": 9936
        },
        "pts_link": "https://tracker.debian.org/pkg/rawstudio",
        "sloc": [
            [
                "ansic",
                43554
            ],
            [
                "cpp",
                20050
            ],
            [
                "xml",
                11152
            ],
            [
                "sh",
                10355
            ],
            [
                "makefile",
                1459
            ]
        ],
        "suites": [
            "wheezy"
        ],
        "vcs_browser": "http://git.debian.org/?p=pkg-phototools/rawstudio.git",
        "vcs_type": "git"
    },
    "raw_url": "/data/main/r/rawstudio/2.0-1.1/pixmaps/rawstudio.png",
    "stat": {
        "perms": "rw-r--r--",
        "size": 4378,
        "symlink_dest": null,
        "type": "-"
    },
    "text_file": false,
    "type": "file",
    "version": "2.0-1.1"
}