{
    "content": [
        {
            "hidden": false,
            "name": "format",
            "stat": {
                "perms": "rw-r--r--",
                "size": 12,
                "symlink_dest": null,
                "type": "-"
            },
            "type": "file"
        },
        {
            "hidden": false,
            "name": "options",
            "stat": {
                "perms": "rw-r--r--",
                "size": 41,
                "symlink_dest": null,
                "type": "-"
            },
            "type": "file"
        }
    ],
    "directory": "source",
    "package": "python-byteplay",
    "path": "python-byteplay/0.2-2/debian/source",
    "pkg_infos": {
        "area": "main",
        "copyright": true,
        "ctags_count": 0,
        "license": "/copyright/license/python-byteplay/0.2-2/",
        "metric": {
            "size": 256
        },
        "pts_link": "https://tracker.debian.org/pkg/python-byteplay",
        "sloc": [
            [
                "python",
                1318
            ],
            [
                "makefile",
                36
            ],
            [
                "sh",
                6
            ]
        ],
        "suites": [
            "wheezy"
        ],
        "vcs_browser": "http://svn.debian.org/viewsvn/python-modules/packages/python-byteplay/trunk/",
        "vcs_type": "svn"
    },
    "type": "directory",
    "version": "0.2-2"
}