{
    "checksum": "0ddbc4a35ef3d1564dae02e896ecd7eaa84b966a35d51ba765c1ccee38b1ae68",
    "file": "Makefile.in",
    "mime": {
        "encoding": "us-ascii",
        "type": "text/x-makefile"
    },
    "number_of_duplicates": 1,
    "package": "miller",
    "path": "miller/5.10.3-1/c/cli/Makefile.in",
    "pkg_infos": {
        "area": "main",
        "copyright": true,
        "ctags_count": 0,
        "license": "/copyright/license/miller/5.10.3-1/",
        "metric": {
            "size": 8832
        },
        "pts_link": "https://tracker.debian.org/pkg/miller",
        "sloc": [
            [
                "ansic",
                56905
            ],
            [
                "sh",
                10221
            ],
            [
                "yacc",
                2286
            ],
            [
                "makefile",
                622
            ]
        ],
        "suites": [
            "bookworm",
            "sid"
        ],
        "vcs_browser": "https://salsa.debian.org/debian/miller",
        "vcs_type": "git"
    },
    "raw_url": "/data/main/m/miller/5.10.3-1/c/cli/Makefile.in",
    "stat": {
        "perms": "rw-r--r--",
        "size": 18357,
        "symlink_dest": null,
        "type": "-"
    },
    "text_file": true,
    "type": "file",
    "version": "5.10.3-1"
}