{
    "checksum": "dbb711529541c991f0d75529cd83fc15c454bd75d7b7f6aa7886a973e57968b1",
    "file": "Makefile.in",
    "mime": {
        "encoding": "us-ascii",
        "type": "text/x-makefile"
    },
    "number_of_duplicates": 1,
    "package": "libnss-nis",
    "path": "libnss-nis/3.1-4/src/Makefile.in",
    "pkg_infos": {
        "area": "main",
        "copyright": true,
        "ctags_count": 0,
        "license": "/copyright/license/libnss-nis/3.1-4/",
        "metric": {
            "size": 1704
        },
        "pts_link": "https://tracker.debian.org/pkg/libnss-nis",
        "sloc": [
            [
                "sh",
                4281
            ],
            [
                "ansic",
                3918
            ],
            [
                "makefile",
                27
            ]
        ],
        "suites": [
            "bookworm",
            "bullseye"
        ],
        "vcs_browser": "https://salsa.debian.org/glibc-team/libnss-nis",
        "vcs_type": "git"
    },
    "raw_url": "/data/main/libn/libnss-nis/3.1-4/src/Makefile.in",
    "stat": {
        "perms": "rw-r--r--",
        "size": 35872,
        "symlink_dest": null,
        "type": "-"
    },
    "text_file": true,
    "type": "file",
    "version": "3.1-4"
}